[{"title":"The Psychology of Money: Timeless Lessons on Wealth, Greed, and Happiness","author":"Morgan Housel","highlightCount":58},{"title":"Let's Talk Money","author":"Monika Halan","highlightCount":139},{"title":"The Penguin History of the World","author":"J M Roberts","highlightCount":27},{"title":"Mary Oliver A Poetry Handbook","author":"Mary Oliver","highlightCount":70},{"title":"Masala Lab","author":"Krish Ashok","highlightCount":279},{"title":"Behave: The Biology of Humans at Our Best and Worst","author":"Robert M. Sapolsky","highlightCount":201},{"title":"Designing Data-Intensive Applications","author":"Martin Kleppmann","highlightCount":75},{"title":"The Picture of Dorian Gray (AmazonClassics Edition)","author":"Oscar Wilde","highlightCount":183},{"title":"Prisoners of Geography","author":"Tim Marshall","highlightCount":1},{"title":"Accelerating Server-Side Development with Fastify","author":"Maksim Sinik;Matteo Collina Manuel Spigolon","highlightCount":6},{"title":"Prisoners of Geography - Tim Marshall","author":"Tim Marshall","highlightCount":1},{"title":"The Etymologicon","author":"Mark Forsyth","highlightCount":42},{"title":"Fredrik Backman - A Man Called Ove","author":"Fredrik Backman","highlightCount":209},{"title":"Stephen Fry - Odyssey","author":"Stephen Fry","highlightCount":88},{"title":"Writing Tools: 55 Essential Strategies for Every Writer","author":"Roy Peter Clark","highlightCount":434},{"title":"The Glamour of Grammar","author":"Roy Peter Clark","highlightCount":1},{"title":"100 Ways to Improve Your Writing (Updated)","author":"Gary Provost","highlightCount":1}]